{"cookies": [{"name": "x-chatium-unique-id", "value": "web-qsjkWFAjlYsGpzBHdnw6c1Qk8QgGjxLY", "domain": "buro20.ru", "path": "/", "expires": 1808225148.575829, "httpOnly": true, "secure": true, "sameSite": "None"}, {"name": "x-chtm-uid", "value": "DNQMeGZxsCBCdFUQsDq2fAVj8VhnxMx-", "domain": "buro20.ru", "path": "/", "expires": 1805201189.633007, "httpOnly": false, "secure": false, "sameSite": "Lax"}, {"name": "x-chtm-uid-sid", "value": "JkutsaWrEbZ-AItm-gBnbu5AkcScViUc:1773665106888", "domain": "buro20.ru", "path": "/", "expires": 1773666989.633141, "httpOnly": false, "secure": false, "sameSite": "Lax"}, {"name": "PHPSESSID5", "value": "770dbf20d29ad4ebc1e2adc3f64e5a39", "domain": ".buro20.ru", "path": "/", "expires": 1776343555.89919, "httpOnly": true, "secure": false, "sameSite": "Lax"}, {"name": "_csrf", "value": "28GPNqGMH0bq587A6P4Oquk6rAzQ2Rsr", "domain": "buro20.ru", "path": "/", "expires": -1, "httpOnly": true, "secure": false, "sameSite": "Lax"}, {"name": "gc_visitor_849911", "value": "%7B%22id%22%3A8836000070%2C%22sfix%22%3A1%7D", "domain": "buro20.ru", "path": "/", "expires": 1805201189.673306, "httpOnly": true, "secure": true, "sameSite": "None"}, {"name": "email_token2", "value": "eyJhbGciOiJIUzI1NiIsInR5cCI6IkpXVCJ9.eyJpZCI6Ikw5Rkd2eWhHU3I3U1dtNGZDWTEwODQ5OTEiLCJpYXQiOjE3NzM2NjUxMTUsImV4cCI6MTc3Mzc1MTU3NX0.NUOJwaJqCZiLnmrL-flA0t5c4ySL1K1P4QgiwNO-Epk", "domain": "buro20.ru", "path": "/", "expires": 1773751557.210598, "httpOnly": true, "secure": true, "sameSite": "Lax"}, {"name": "gc_visit_849911", "value": "%7B%22id%22%3A15152649120%2C%22sid%22%3A9181480735%7D", "domain": "buro20.ru", "path": "/", "expires": 1773666957.476383, "httpOnly": true, "secure": true, "sameSite": "None"}, {"name": "dd_bdfhyr", "value": "e47a02496e8865880c918e2324b8b5be", "domain": "buro20.ru", "path": "/", "expires": 1773751589.741834, "httpOnly": true, "secure": true, "sameSite": "None"}, {"name": "gc_counter_849911", "value": "%7B%22id%22%3A9181480735%2C%22last_activity%22%3A%222026-03-16%2015%3A45%3A48%22%2C%22user_id%22%3A492984604%2C%22utm_id%22%3Anull%2C%22partner_code_id%22%3Anull%2C%22ad_offer_id%22%3Anull%2C%22fuid%22%3Anull%2C%22fpid%22%3Anull%2C%22city_id%22%3Anull%7D", "domain": "buro20.ru", "path": "/", "expires": 1776257189.67322, "httpOnly": true, "secure": true, "sameSite": "None"}], "origins": [{"origin": "https://buro20.ru", "localStorage": [{"name": "tusSupport", "value": "null"}, {"name": "visitor", "value": "{\"id\":8836000070,\"sfix\":1}"}, {"name": "visit", "value": "{\"id\":15152649120,\"sid\":9181480735}"}, {"name": "session", "value": "{\"id\":9181480735,\"last_activity\":\"2026-03-16 15:45:48\",\"user_id\":492984604,\"utm_id\":null}"}, {"name": "hash", "value": "889cd26e76da5e71ee83f4398ff43616"}]}]}